sdclient/__init__.py
sdclient/client.py
sdclient/date_utils.py
sdclient/exceptions.py
sdclient/py.typed
sdclient/requests.py
sdclient/responses.py
another_sd_client-5.0.0.dist-info/METADATA
another_sd_client-5.0.0.dist-info/WHEEL
another_sd_client-5.0.0.dist-info/RECORD
