Metadata-Version: 2.4
Name: another-sd-client
Version: 5.0.0
Summary: Client for communicating with SD Løn
Keywords: os2mo,sd
Author: Magenta ApS
Author-email: info@magenta.dk
Requires-Python: >=3.11,<4.0
Classifier: Programming Language :: Python :: 3
Classifier: Programming Language :: Python :: 3.11
Classifier: Programming Language :: Python :: 3.12
Classifier: Programming Language :: Python :: 3.13
Classifier: Programming Language :: Python :: 3.14
Requires-Dist: click (>=8.1.3,<9.0.0)
Requires-Dist: httpx (>=0.22.0)
Requires-Dist: lxml (>=4.9.2,<5.0.0)
Requires-Dist: more-itertools (>=8.14.0)
Requires-Dist: pydantic (>=1.10.4,<2.0.0)
Requires-Dist: structlog (>=25,<26)
Requires-Dist: xmltodict (>=0.12.0)
Project-URL: Homepage, https://magenta.dk/
Project-URL: Repository, https://git.magenta.dk/rammearkitektur/another-sd-client
